Workbook
Name income: #REF!
Name Range_EV: #REF!
Name range_ICE: #REF!

Sheet About
A1: BNoEVC BAU Number of EV Chargers | B1: South Carolina | C1: 46184 | F1: Alabama | G1: AL
B2: =LOOKUP(B1,F1:G50,G1:G50) -> SC | F2: Alaska | G2: AK
A3: Source: | B3: Number of Gas pumps | F3: Arizona | G3: AZ
B4: CleanTechnica | F4: Arkansas | G4: AR
B5: 2018 | F5: California | G5: CA
B6: Stop Comparing the Number of Gas Stations to EV Charging Stations | F6: Colorado | G6: CO
B7: https://cleantechnica.com/2018/03/07/stop-comparing-number-gas-stations-ev-charging-stations/ | F7: Connecticut | G7: CT
F8: Delaware | G8: DE
B9: Number of EVSE Ports | F9: Florida | G9: FL
B10: Alternative Fuels Data Center | F10: Georgia | G10: GA
B11: 2023 | F11: Hawaii | G11: HI
B12: Electric Vehicle Charging Station Locations | F12: Idaho | G12: ID
B13: https://afdc.energy.gov/fuels/electricity_locations.html#/analyze?fuel=ELEC&country=US | F13: Illinois | G13: IL
F14: Indiana | G14: IN
A15: Notes | F15: Iowa | G15: IA
A16: Currency Conversion | B16: 0.89805482 | F16: Kansas | G16: KS
A17: 2019 to 2012 USD | B17: 0.84730413 | F17: Kentucky | G17: KY
A18: 2021 to 2012 USD | B18: 0.785 | F18: Louisiana | G18: LA
A19: 2022 to 2012 USD | F19: Maine | G19: ME
F20: Maryland | G20: MD
A21: We assume that prior to the IIJA or IRA, the number of EV ports would slowly grow with time to equal the number of gas pumps by 2050. | F21: Massachusetts | G21: MA
A22: We adjust our calculations by an estimated number of public charger additions from both the Infrastructure Investment and Jobs Act | F22: Michigan | G22: MI
A23: and the Inflation Reduction Act (see tabs for methodology). | F23: Minnesota | G23: MN
F24: Mississippi | G24: MS
F25: Missouri | G25: MO
F26: Montana | G26: MT
F27: Nebraska | G27: NE
F28: Nevada | G28: NV
F29: New Hampshire | G29: NH
F30: New Jersey | G30: NJ
F31: New Mexico | G31: NM
F32: New York | G32: NY
F33: North Carolina | G33: NC
F34: North Dakota | G34: ND
F35: Ohio | G35: OH
... F50: Wyoming | G50: WY

Sheet EV Charger S-Curve
A1: US Public EV Charging Ports — Historical Data & Logistic (S-Curve) Forecast
A2: Source: AFDC / NREL, Alternative Fuels Data Center (afdc.energy.gov/data/10972). VERIFY against primary source before use.
A4: Logistic Parameters (editable inputs)
A5: L — saturation ceiling (max ports) | B5: 1200000 | C5: ASSUMPTION — not fitted from data; L is essentially unidentifiable from the historical series alone. Scenario this from an external source.
A6: k — growth rate (steepness) | B6: 0.27
A7: t0 — inflection year (midpoint) | B7: 2027 | C7: Logistic: P(t) = L / (1 + EXP(-k*(t - t0)))
A9: Year | B9: Actual Ports (historical) | C9: S-Curve Forecast | D9: YoY Growth (forecast)
A10: 2011 | B10: 5248 | C10: =$B$5/(1+EXP(-$B$6*(A10-$B$7))) -> 15750.382
A11: 2012 | B11: 12726 | C11: =$B$5/(1+EXP(-$B$6*(A11-$B$7))) -> 20548.84 | D11: =C11/C10-1 -> 0.30465661
A12: 2013 | B12: 16619 | C12: =$B$5/(1+EXP(-$B$6*(A12-$B$7))) -> 26776.126 | D12: =C12/C11-1 -> 0.30304808
A13: 2014 | B13: 22247 | C13: =$B$5/(1+EXP(-$B$6*(A13-$B$7))) -> 34834.843 | D13: =C13/C12-1 -> 0.30096648
A14: 2015 | B14: 29968 | C14: =$B$5/(1+EXP(-$B$6*(A14-$B$7))) -> 45225.469 | D14: =C14/C13-1 -> 0.29828254
A15: 2016 | B15: 38543 | C15: =$B$5/(1+EXP(-$B$6*(A15-$B$7))) -> 58559.668 | D15: =C15/C14-1 -> 0.29483827
A16: 2017 | B16: 46218 | C16: =$B$5/(1+EXP(-$B$6*(A16-$B$7))) -> 75568.027 | D16: =C16/C15-1 -> 0.29044495
A17: 2018 | B17: 57386 | C17: =$B$5/(1+EXP(-$B$6*(A17-$B$7))) -> 97096.161 | D17: =C17/C16-1 -> 0.28488415
A18: 2019 | B18: 75808 | C18: =$B$5/(1+EXP(-$B$6*(A18-$B$7))) -> 124080.54 | D18: =C18/C17-1 -> 0.27791399
A19: 2020 | B19: 96521 | C19: =$B$5/(1+EXP(-$B$6*(A19-$B$7))) -> 157493.36 | D19: =C19/C18-1 -> 0.26928333
A20: 2021 | B20: 114715 | C20: =$B$5/(1+EXP(-$B$6*(A20-$B$7))) -> 198245.84 | D20: =C20/C19-1 -> 0.25875681
A21: 2022 | B21: 136307 | C21: =$B$5/(1+EXP(-$B$6*(A21-$B$7))) -> 247044.45 | D21: =C21/C20-1 -> 0.24615195
A22: 2023 | B22: 168388 | C22: =$B$5/(1+EXP(-$B$6*(A22-$B$7))) -> 304207.22 | D22: =C22/C21-1 -> 0.2313866
A23: 2024 | C23: =$B$5/(1+EXP(-$B$6*(A23-$B$7))) -> 369468.59 | D23: =C23/C22-1 -> 0.21452934
A24: 2025 | C24: =$B$5/(1+EXP(-$B$6*(A24-$B$7))) -> 441825.1 | D24: =C24/C23-1 -> 0.19583939
A25: 2026 | C25: =$B$5/(1+EXP(-$B$6*(A25-$B$7))) -> 519488.51 | D25: =C25/C24-1 -> 0.17577864
A26: 2027 | C26: =$B$5/(1+EXP(-$B$6*(A26-$B$7))) -> 600000 | D26: =C26/C25-1 -> 0.15498223
A27: 2028 | C27: =$B$5/(1+EXP(-$B$6*(A27-$B$7))) -> 680511.49 | D27: =C27/C26-1 -> 0.13418581
A28: 2029 | C28: =$B$5/(1+EXP(-$B$6*(A28-$B$7))) -> 758174.9 | D28: =C28/C27-1 -> 0.11412506
A29: 2030 | C29: =$B$5/(1+EXP(-$B$6*(A29-$B$7))) -> 830531.41 | D29: =C29/C28-1 -> 0.095435108
A30: 2031 | C30: =$B$5/(1+EXP(-$B$6*(A30-$B$7))) -> 895792.78 | D30: =C30/C29-1 -> 0.078577853
A31: 2032 | C31: =$B$5/(1+EXP(-$B$6*(A31-$B$7))) -> 952955.55 | D31: =C31/C30-1 -> 0.063812497
A32: 2033 | C32: =$B$5/(1+EXP(-$B$6*(A32-$B$7))) -> 1001754.2 | D32: =C32/C31-1 -> 0.051207637
A33: 2034 | C33: =$B$5/(1+EXP(-$B$6*(A33-$B$7))) -> 1042506.6 | D33: =C33/C32-1 -> 0.04068112
A34: 2035 | C34: =$B$5/(1+EXP(-$B$6*(A34-$B$7))) -> 1075919.5 | D34: =C34/C33-1 -> 0.032050464
A36: Notes:
A37: • Blue cells are inputs you can change; the S-Curve column recalculates automatically.
A38: • 2022 definitional change: ports now include temporarily-unavailable units, creating a small discontinuity.
A39: • Parameters are illustrative, not rigorously fitted. For a real fit, constrain L from a vehicle-stock or published charger-need model and fit k, t0 via Solver/regression.
A40: • This is a starting point for staff review, not a finished EI work product.

Sheet alt_fuel_stations (Jun 5 2026)
A1: Fuel Type Code | B1: State | C1: EV Level1 EVSE Num | D1: EV Level2 EVSE Num | E1: EV DC Fast Count | F1: TOTAL
A2: ELEC | B2: CA | D2: 8 | F2: =SUM(C2:E2) -> 8
A3: ELEC | B3: CA | D3: 1 | F3: =SUM(C3:E3) -> 1
A4: ELEC | B4: CA | D4: 2 | F4: =SUM(C4:E4) -> 2
A5: ELEC | B5: CA | D5: 4 | F5: =SUM(C5:E5) -> 4
A6: ELEC | B6: CA | D6: 26 | F6: =SUM(C6:E6) -> 26
A7: ELEC | B7: CA | D7: 3 | F7: =SUM(C7:E7) -> 3
A8: ELEC | B8: CA | D8: 3 | F8: =SUM(C8:E8) -> 3
A9: ELEC | B9: CA | D9: 1 | F9: =SUM(C9:E9) -> 1
A10: ELEC | B10: CA | D10: 20 | F10: =SUM(C10:E10) -> 20
A11: ELEC | B11: CA | D11: 1 | F11: =SUM(C11:E11) -> 1
A12: ELEC | B12: CA | D12: 2 | F12: =SUM(C12:E12) -> 2
A13: ELEC | B13: CA | D13: 4 | F13: =SUM(C13:E13) -> 4
... A16: ELEC | B16: CA | D16: 3 | F16: =SUM(C16:E16) -> 3
A17: ELEC | B17: CA | C17: 1 | D17: 10 | F17: =SUM(C17:E17) -> 11
A18: ELEC | B18: CA | D18: 4 | F18: =SUM(C18:E18) -> 4
A19: ELEC | B19: CA | D19: 1 | F19: =SUM(C19:E19) -> 1
A20: ELEC | B20: CA | D20: 4 | F20: =SUM(C20:E20) -> 4
A21: ELEC | B21: CA | D21: 2 | F21: =SUM(C21:E21) -> 2
A22: ELEC | B22: CA | D22: 1 | F22: =SUM(C22:E22) -> 1
A23: ELEC | B23: CA | D23: 2 | F23: =SUM(C23:E23) -> 2
A24: ELEC | B24: CA | D24: 2 | F24: =SUM(C24:E24) -> 2
A25: ELEC | B25: CA | D25: 4 | F25: =SUM(C25:E25) -> 4
A26: ELEC | B26: CA | D26: 4 | F26: =SUM(C26:E26) -> 4
A27: ELEC | B27: CA | C27: 12 | D27: 15 | F27: =SUM(C27:E27) -> 27
A28: ELEC | B28: CA | D28: 3 | F28: =SUM(C28:E28) -> 3
A29: ELEC | B29: CA | D29: 6 | F29: =SUM(C29:E29) -> 6
A30: ELEC | B30: CA | D30: 8 | F30: =SUM(C30:E30) -> 8
A31: ELEC | B31: CA | D31: 5 | F31: =SUM(C31:E31) -> 5
A32: ELEC | B32: CA | D32: 4 | F32: =SUM(C32:E32) -> 4
A33: ELEC | B33: CA | C33: 4 | D33: 2 | F33: =SUM(C33:E33) -> 6
A34: ELEC | B34: CA | D34: 1 | F34: =SUM(C34:E34) -> 1
A35: ELEC | B35: CA | D35: 2 | F35: =SUM(C35:E35) -> 2
A36: ELEC | B36: CA | D36: 3 | F36: =SUM(C36:E36) -> 3
A37: ELEC | B37: CA | D37: 3 | F37: =SUM(C37:E37) -> 3
A38: ELEC | B38: CA | C38: 1 | D38: 3 | F38: =SUM(C38:E38) -> 4
A39: ELEC | B39: CA | D39: 2 | F39: =SUM(C39:E39) -> 2
A40: ELEC | B40: CA | C40: 1 | D40: 2 | F40: =SUM(C40:E40) -> 3
A41: ELEC | B41: CA | D41: 1 | F41: =SUM(C41:E41) -> 1
A42: ELEC | B42: CA | D42: 2 | F42: =SUM(C42:E42) -> 2
A43: ELEC | B43: CA | D43: 2 | F43: =SUM(C43:E43) -> 2
A44: ELEC | B44: CA | D44: 1 | F44: =SUM(C44:E44) -> 1
A45: ELEC | B45: CA | D45: 4 | F45: =SUM(C45:E45) -> 4
A46: ELEC | B46: CA | D46: 2 | F46: =SUM(C46:E46) -> 2
A47: ELEC | B47: CA | D47: 2 | F47: =SUM(C47:E47) -> 2
A48: ELEC | B48: CA | D48: 1 | F48: =SUM(C48:E48) -> 1
A49: ELEC | B49: CA | D49: 7 | F49: =SUM(C49:E49) -> 7
A50: ELEC | B50: CA | D50: 4 | F50: =SUM(C50:E50) -> 4
A51: ELEC | B51: CA | D51: 3 | F51: =SUM(C51:E51) -> 3
A52: ELEC | B52: CA | D52: 2 | F52: =SUM(C52:E52) -> 2
... A59: ELEC | B59: VT | D59: 6 | F59: =SUM(C59:E59) -> 6
A60: ELEC | B60: OR | C60: 2 | D60: 2 | F60: =SUM(C60:E60) -> 4
A61: ELEC | B61: CA | C61: 1 | D61: 1 | F61: =SUM(C61:E61) -> 2
A62: ELEC | B62: CA | D62: 2 | F62: =SUM(C62:E62) -> 2
A63: ELEC | B63: CA | D63: 2 | F63: =SUM(C63:E63) -> 2
A64: ELEC | B64: CA | C64: 3 | D64: 7 | F64: =SUM(C64:E64) -> 10
A65: ELEC | B65: CA | D65: 1 | F65: =SUM(C65:E65) -> 1
A66: ELEC | B66: CA | D66: 2 | F66: =SUM(C66:E66) -> 2
A67: ELEC | B67: CA | D67: 2 | F67: =SUM(C67:E67) -> 2
A68: ELEC | B68: CA | D68: 2 | F68: =SUM(C68:E68) -> 2
A69: ELEC | B69: CA | D69: 2 | F69: =SUM(C69:E69) -> 2
A70: ELEC | B70: WA | D70: 68 | F70: =SUM(C70:E70) -> 68
A71: ELEC | B71: IL | D71: 4 | F71: =SUM(C71:E71) -> 4
A72: ELEC | B72: ID | D72: 2 | F72: =SUM(C72:E72) -> 2
A73: ELEC | B73: OR | D73: 2 | F73: =SUM(C73:E73) -> 2
A74: ELEC | B74: WI | D74: 2 | F74: =SUM(C74:E74) -> 2
A75: ELEC | B75: OR | D75: 2 | F75: =SUM(C75:E75) -> 2
A76: ELEC | B76: CA | D76: 5 | F76: =SUM(C76:E76) -> 5
A77: ELEC | B77: CA | D77: 4 | F77: =SUM(C77:E77) -> 4
A78: ELEC | B78: WA | C78: 1 | D78: 2 | F78: =SUM(C78:E78) -> 3
A79: ELEC | B79: WA | D79: 6 | F79: =SUM(C79:E79) -> 6
A80: ELEC | B80: IA | D80: 1 | F80: =SUM(C80:E80) -> 1
A81: ELEC | B81: IA | D81: 1 | F81: =SUM(C81:E81) -> 1
A82: ELEC | B82: OR | C82: 20 | D82: 20 | F82: =SUM(C82:E82) -> 40
A83: ELEC | B83: TX | D83: 2 | F83: =SUM(C83:E83) -> 2
A84: ELEC | B84: SC | D84: 2 | F84: =SUM(C84:E84) -> 2
A85: ELEC | B85: SC | D85: 2 | F85: =SUM(C85:E85) -> 2
A86: ELEC | B86: SC | D86: 2 | F86: =SUM(C86:E86) -> 2
A87: ELEC | B87: CT | D87: 2 | F87: =SUM(C87:E87) -> 2
A88: ELEC | B88: CT | C88: 2 | D88: 4 | F88: =SUM(C88:E88) -> 6
A89: ELEC | B89: CT | C89: 1 | D89: 1 | F89: =SUM(C89:E89) -> 2
A90: ELEC | B90: WI | D90: 2 | F90: =SUM(C90:E90) -> 2
A91: ELEC | B91: WI | D91: 2 | F91: =SUM(C91:E91) -> 2
A92: ELEC | B92: OH | D92: 1 | F92: =SUM(C92:E92) -> 1
A93: ELEC | B93: WV | D93: 2 | F93: =SUM(C93:E93) -> 2
A94: ELEC | B94: MO | D94: 1 | F94: =SUM(C94:E94) -> 1
A95: ELEC | B95: OR | D95: 2 | F95: =SUM(C95:E95) -> 2
A96: ELEC | B96: OR | D96: 2 | F96: =SUM(C96:E96) -> 2
A97: ELEC | B97: WA | D97: 2 | F97: =SUM(C97:E97) -> 2
A98: ELEC | B98: GA | D98: 6 | F98: =SUM(C98:E98) -> 6
A99: ELEC | B99: OR | D99: 1 | F99: =SUM(C99:E99) -> 1
A100: ELEC | B100: UT | D100: 4 | F100: =SUM(C100:E100) -> 4
A101: ELEC | B101: KS | D101: 2 | F101: =SUM(C101:E101) -> 2
... A115: ELEC | B115: SC | D115: 2 | F115: =SUM(C115:E115) -> 2
A116: ELEC | B116: SC | D116: 2 | E116: 1 | F116: =SUM(C116:E116) -> 3
A117: ELEC | B117: SC | D117: 2 | F117: =SUM(C117:E117) -> 2
A118: ELEC | B118: SC | D118: 6 | F118: =SUM(C118:E118) -> 6
A119: ELEC | B119: CA | D119: 3 | F119: =SUM(C119:E119) -> 3
A120: ELEC | B120: CA | D120: 12 | E120: 2 | F120: =SUM(C120:E120) -> 14
A121: ELEC | B121: CO | C121: 18 | D121: 9 | E121: 1 | F121: =SUM(C121:E121) -> 28
...

Sheet 2022
A1: Station Counts by State and Fuel Type
A2: State | B2: Electrica
B3: (stations / charging outlets
B4: Level 1 / Level 2 / DC Fast)
A5: Alabama | B5: 326 | C5: 848
B6: 35 | C6: 574 | D6: 239
A7: Alaska | B7: 62 | C7: 115
B8: 3 | C8: 81 | D8: 31
A9: Arizona | B9: 977 | C9: 2638
B10: 9 | C10: 2036 | D10: 593
A11: Arkansas | B11: 222 | C11: 598
B12: 3 | C12: 516 | D12: 79
A13: California | B13: 14616 | C13: 43400
B14: 546 | C14: 34359 | D14: 8465
A15: Colorado | B15: 1788 | C15: 4411
B16: 90 | C16: 3588 | D16: 733
A17: Connecticut | B17: 593 | C17: 1638
B18: 67 | C18: 1220 | D18: 349
A19: Delaware | B19: 156 | C19: 367
B20: 5 | C20: 257 | D20: 105
A21: District of Columbia | B21: 300 | C21: 970
B22: 43 | C22: 889 | D22: 38
A23: Florida | B23: 2913 | C23: 7802
B24: 364 | C24: 5823 | D24: 1615
A25: Georgia | B25: 1550 | C25: 4121
B26: 230 | C26: 3097 | D26: 794
A27: Hawaii | B27: 406 | C27: 940
B28: 30 | C28: 833 | D28: 77
A29: Idaho | B29: 155 | C29: 382
B30: 10 | C30: 285 | D30: 87
A31: Illinois | B31: 1328 | C31: 3315
B32: 50 | C32: 2593 | D32: 672
A33: Indiana | B33: 400 | C33: 1088
B34: 8 | C34: 743 | D34: 337
A35: Iowa | B35: 305 | C35: 659
B36: 4 | C36: 420 | D36: 235
A37: Kansas | B37: 491 | C37: 1047
B38: 14 | C38: 878 | D38: 155
A39: Kentucky | B39: 252 | C39: 616
B40: 24 | C40: 481 | D40: 111
A41: Louisiana | B41: 193 | C41: 475
B42: 21 | C42: 328 | D42: 126
A43: Maine | B43: 408 | C43: 865
B44: 25 | C44: 663 | D44: 177
A45: Maryland | B45: 1373 | C45: 3929
B46: 45 | C46: 3203 | D46: 681
A47: Massachusetts | B47: 2416 | C47: 5765
B48: 64 | C48: 5125 | D48: 576
A49: Michigan | B49: 1147 | C49: 2697
B50: 14 | C50: 2145 | D50: 528
A51: Minnesota | B51: 594 | C51: 1517
B52: 75 | C52: 1177 | D52: 265
A53: Mississippi | B53: 115 | C53: 441
B54: 139 | C54: 221 | D54: 81
A55: Missouri | B55: 1031 | C55: 2212
B56: 14 | C56: 1908 | D56: 290
A57: Montana | B57: 98 | C57: 252
B58: 3 | C58: 141 | D58: 108
A59: Nebraska | B59: 214 | C59: 446
B60: 0 | C60: 340 | D60: 106
A61: Nevada | B61: 478 | C61: 1663
B62: 15 | C62: 1222 | D62: 426
A63: New Hampshire | B63: 202 | C63: 468
B64: 6 | C64: 324 | D64: 138
A65: New Jersey | B65: 939 | C65: 2694
B66: 16 | C66: 1967 | D66: 711
A67: New Mexico | B67: 201 | C67: 508
B68: 10 | C68: 339 | D68: 159
A69: New York | B69: 3327 | C69: 9539
B70: 41 | C70: 8342 | D70: 1156
A71: North Carolina | B71: 1154 | C71: 3031
B72: 37 | C72: 2300 | D72: 694
A73: North Dakota | B73: 80 | C73: 172
B74: 0 | C74: 111 | D74: 61
A75: Ohio | B75: 1242 | C75: 2801
B76: 40 | C76: 2325 | D76: 436
A77: Oklahoma | B77: 341 | C77: 1093
B78: 8 | C78: 455 | D78: 630
A79: Oregon | B79: 1007 | C79: 2472
B80: 75 | C80: 1917 | D80: 480
A81: Pennsylvania | B81: 1330 | C81: 3247
B82: 51 | C82: 2508 | D82: 688
A83: Rhode Island | B83: 296 | C83: 772
B84: 82 | C84: 623 | D84: 67
A85: South Carolina | B85: 417 | C85: 987
B86: 18 | C86: 708 | D86: 261
A87: South Dakota | B87: 69 | C87: 176
B88: 2 | C88: 96 | D88: 78
A89: Tennessee | B89: 686 | C89: 1674
B90: 33 | C90: 1377 | D90: 264
A91: Texas | B91: 2472 | C91: 6313
B92: 96 | C92: 4831 | D92: 1386
A93: Utah | B93: 782 | C93: 1857
B94: 17 | C94: 1584 | D94: 256
A95: Vermont | B95: 349 | C95: 896
B96: 35 | C96: 758 | D96: 103
A97: Virginia | B97: 1227 | C97: 3651
B98: 237 | C98: 2528 | D98: 886
A99: Washington | B99: 1777 | C99: 4520
B100: 209 | C100: 3500 | D100: 811
...

Sheet calcs
A1: STATE | B1: =About!B2 -> SC | C1: =About!B1 -> South Carolina
B3: 2022 | C3: 2025
A4: EV charger | B4: =SUMIFS('2022'!C:C,'2022'!A:A,calcs!C1) -> 987 | C4: =SUMIFS('alt_fuel_stations (Jun 5 2026)'!F:F,'alt_fuel_stations (Jun 5 2026)'!B:B,calcs!B1) -> 2083
B6: 2022 | C6: 2023 | D6: 2024 | E6: 2025 | F6: 2026 | G6: 2027 | H6: 2028 | I6: 2029 | J6: 2030 | K6: 2031 | L6: 2032 | M6: 2033 | N6: 2034 | O6: 2035
A7: GROWTH | B7: {=TRANSPOSE('EV Charger S-Curve'!D21:D34)} -> 0.24615195 | C7: 0.2313866 | D7: 0.21452934 | E7: 0.19583939 | F7: 0.17577864 | G7: 0.15498223 | H7: 0.13418581 | I7: 0.11412506 | J7: 0.095435108 | K7: 0.078577853 | L7: 0.063812497 | M7: 0.051207637 | N7: 0.04068112 | O7: 0.032050464
B10: 2022 | C10: 2023 | D10: 2024 | E10: 2025 | F10: 2026 | G10: 2027 | H10: 2028 | I10: 2029 | J10: 2030 | K10: 2031 | L10: 2032 | M10: 2033 | N10: 2034 | O10: 2035 | P10: 2036 | Q10: 2037 | R10: 2038 | S10: 2039 | T10: 2040 | U10: 2041 | V10: 2042 | W10: 2043 | X10: 2044 | Y10: 2045 | Z10: 2046 | AA10: 2047 | AB10: 2048 | AC10: 2049 | AD10: 2050
A11: EV charger | B11: =_xlfn.FORECAST.ETS(B10,$B$4:$C$4,$B$3:$C$3) -> 987 | C11: =_xlfn.FORECAST.ETS(C10,$B$4:$C$4,$B$3:$C$3) -> 1352.3333 | D11: =ROUND(C11*(1+'EV Charger S-Curve'!D22),0) -> 1665 | E11: =C4 -> 2083 | F11: =ROUND(E11*(1+F7),0) -> 2449 | G11: =ROUND(F11*(1+G7),0) -> 2829 | H11: =ROUND(G11*(1+H7),0) -> 3209 | I11: =ROUND(H11*(1+I7),0) -> 3575 | J11: =ROUND(I11*(1+J7),0) -> 3916 | K11: =ROUND(J11*(1+K7),0) -> 4224 | L11: =ROUND(K11*(1+L7),0) -> 4494 | M11: =ROUND(L11*(1+M7),0) -> 4724 | ... O11: =ROUND(N11*(1+O7),0) -> 5074 | P11: =ROUND(_xlfn.FORECAST.ETS(P10,$J$11:$O$11,$J$10:$O$10),0) -> 5298 | Q11: =ROUND(_xlfn.FORECAST.ETS(Q10,$J$11:$O$11,$J$10:$O$10),0) -> 5523 | R11: =ROUND(_xlfn.FORECAST.ETS(R10,$J$11:$O$11,$J$10:$O$10),0) -> 5747 | S11: =ROUND(_xlfn.FORECAST.ETS(S10,$J$11:$O$11,$J$10:$O$10),0) -> 5971 | T11: =ROUND(_xlfn.FORECAST.ETS(T10,$J$11:$O$11,$J$10:$O$10),0) -> 6195 | U11: =ROUND(_xlfn.FORECAST.ETS(U10,$J$11:$O$11,$J$10:$O$10),0) -> 6419 | V11: =ROUND(_xlfn.FORECAST.ETS(V10,$J$11:$O$11,$J$10:$O$10),0) -> 6644 | W11: =ROUND(_xlfn.FORECAST.ETS(W10,$J$11:$O$11,$J$10:$O$10),0) -> 6868 | ... AD11: =ROUND(_xlfn.FORECAST.ETS(AD10,$J$11:$O$11,$J$10:$O$10),0) -> 8437

Sheet BNoEVC
A1: Number of chargers | B1: 2024 | C1: 2025 | D1: 2026 | E1: 2027 | F1: 2028 | G1: 2029 | H1: 2030 | I1: 2031 | J1: 2032 | K1: 2033 | L1: 2034 | M1: 2035 | N1: 2036 | O1: 2037 | P1: 2038 | Q1: 2039 | R1: 2040 | S1: 2041 | T1: 2042 | U1: 2043 | V1: 2044 | W1: 2045 | X1: 2046 | Y1: 2047 | Z1: 2048 | AA1: 2049 | AB1: 2050
A2: BAU EV Chargers | B2: =calcs!D11 -> 1665 | C2: =calcs!E11 -> 2083 | D2: =calcs!F11 -> 2449 | E2: =calcs!G11 -> 2829 | F2: =calcs!H11 -> 3209 | G2: =calcs!I11 -> 3575 | H2: =calcs!J11 -> 3916 | I2: =calcs!K11 -> 4224 | ... AB2: =calcs!AD11 -> 8437
